pysystems/__init__.py
pysystems-1.1.0.dist-info/LICENSE
pysystems-1.1.0.dist-info/METADATA
pysystems-1.1.0.dist-info/WHEEL
pysystems-1.1.0.dist-info/top_level.txt
pysystems-1.1.0.dist-info/RECORD
