Metadata-Version: 2.1
Name: pysystems
Version: 1.1.0
Summary: A python package to solve multi-varible systems of equations
Home-page: https://github.com/gubareve/pysystems/
Author: Evan Gubarev
Author-email: evan@evangubarev.com
License: GNU
Platform: UNKNOWN
Requires-Dist: numpy
